llama_index/readers/legacy_office/__init__.py
llama_index/readers/legacy_office/reader.py
llama_index_readers_legacy_office-0.2.1.dist-info/METADATA
llama_index_readers_legacy_office-0.2.1.dist-info/WHEEL
llama_index_readers_legacy_office-0.2.1.dist-info/RECORD
