Metadata-Version: 2.4
Name: llama-index-readers-legacy-office
Version: 0.2.1
Summary: LlamaIndex Legacy Office Reader, handles .doc files loading with Apache Tika
Author-email: Your Name <you@example.com>
License-Expression: MIT
Requires-Python: <4.0,>=3.9
Requires-Dist: llama-index-core<0.15,>=0.13.0
Requires-Dist: tika>=2.6.0
